kpis_query_generation/__init__.py
kpis_query_generation/generate_templates_and_params.py
kpis_query_generation/return_summary/__init__.py
kpis_query_generation/return_summary/sql_templates.py
kpis_query_generation/return_trend/__init__.py
kpis_query_generation/return_trend/sql_templates.py
kpis_query_generation/utils/__init__.py
kpis_query_generation/utils/query_templating/__init__.py
kpis_query_generation/utils/query_templating/computed_field_util.py
kpis_query_generation/utils/query_templating/computed_fileds_config.py
kpis_query_generation/utils/query_templating/cte_util.py
kpis_query_generation/utils/query_templating/query_utils.py
kpisQueryGeneration-0.1.7.dist-info/METADATA
kpisQueryGeneration-0.1.7.dist-info/WHEEL
kpisQueryGeneration-0.1.7.dist-info/top_level.txt
kpisQueryGeneration-0.1.7.dist-info/RECORD
